elastixpy/__init__.py
elastixpy/elastix.py
elastixpy-0.2.5.dist-info/LICENSE
elastixpy-0.2.5.dist-info/WHEEL
elastixpy-0.2.5.dist-info/METADATA
elastixpy-0.2.5.dist-info/RECORD
